sahibinden/__init__.py
sahibinden/configuration.py
sahibinden/sahibinden.py
sahibinden_pkg-0.0.8.1.dist-info/METADATA
sahibinden_pkg-0.0.8.1.dist-info/WHEEL
sahibinden_pkg-0.0.8.1.dist-info/top_level.txt
sahibinden_pkg-0.0.8.1.dist-info/RECORD
