Metadata-Version: 2.1
Name: sahibinden-pkg
Version: 0.0.8.1
Summary: Sample Data Processing of Sahibinden
Home-page: https://pypi.org/project/sahibinden-pkg/
Author: Servet Guney
Author-email: servetguney@gmail.com
License: MIT
Platform: UNKNOWN
Requires-Dist: setuptools (>=42)
Requires-Dist: requests
Requires-Dist: beautifulsoup4
Requires-Dist: statistics
Requires-Dist: soupsieve
Requires-Dist: lxml
Requires-Dist: wheel
Requires-Dist: numpy
